setup.cfg
setup.py
pymomo/__init__.py
pymomo/__version__.py
pymomo/exceptions.py
pymomo.egg-info/PKG-INFO
pymomo.egg-info/SOURCES.txt
pymomo.egg-info/dependency_links.txt
pymomo.egg-info/entry_points.txt
pymomo.egg-info/requires.txt
pymomo.egg-info/top_level.txt
pymomo/commander/__init__.py
pymomo/commander/cmdstream.py
pymomo/commander/exceptions.py
pymomo/commander/commands/__init__.py
pymomo/commander/commands/command.py
pymomo/commander/commands/rpc.py
pymomo/commander/hwtest/__init__.py
pymomo/commander/hwtest/fixtures.py
pymomo/commander/hwtest/features/__init__.py
pymomo/commander/hwtest/features/test_firmware_cache.py
pymomo/commander/meta/__init__.py
pymomo/commander/meta/initialization.py
pymomo/commander/meta/reflash.py
pymomo/commander/proxy/__init__.py
pymomo/commander/proxy/controller.py
pymomo/commander/proxy/gsm.py
pymomo/commander/proxy/multisensor.py
pymomo/commander/proxy/proxy.py
pymomo/commander/proxy/proxy12.py
pymomo/commander/transport/__init__.py
pymomo/commander/transport/serialtrans.py
pymomo/commander/transport/transport.py
pymomo/commander/types/__init__.py
pymomo/commander/types/mod_descriptor.py
pymomo/commander/types/perfcount.py
pymomo/commander/types/sensor_event.py
pymomo/config/README.md
pymomo/config/build_settings.json
pymomo/config/known_features.mib
pymomo/config/pcb_library.global.json
pymomo/config/pcb/eagle.json
pymomo/config/resources/bom_formatting/excel-2007-header-bg.gif
pymomo/config/resources/bom_formatting/excel-2007-header-left.gif
pymomo/config/resources/bom_formatting/excel-2007.css
pymomo/config/site_scons/__init__.py
pymomo/config/site_scons/autobuild.py
pymomo/config/site_scons/autobuild.pyc
pymomo/config/site_scons/cfileparser.py
pymomo/config/site_scons/cfileparser.pyc
pymomo/config/site_scons/pic12.py
pymomo/config/site_scons/pic12.pyc
pymomo/config/site_scons/pic12_unit.py
pymomo/config/site_scons/pic12_unit.pyc
pymomo/config/site_scons/pic24.py
pymomo/config/site_scons/pic24.pyc
pymomo/config/site_scons/reference.py
pymomo/config/site_scons/site_init.py
pymomo/config/site_scons/test_summary.py
pymomo/config/site_scons/test_summary.pyc
pymomo/config/site_scons/unit_test.py
