Metadata-Version: 1.1
Name: pymomo
Version: 1.1.2
Summary: WellDone Mobile Monitor (MoMo) Interaction Library
Home-page: http://github.com/welldone/pymomo
Author: WellDone International
Author-email: info@welldone.org
License: LGPLv3
Keywords: momo,remote,monitoring,embedded,hardware
Platform: UNKNOWN
Classifier: Programming Language :: Python
Classifier: Development Status :: 5 - Production/Stable
Classifier: License :: OSI Approved :: GNU Library or Lesser General Public License (LGPL)
Classifier: Operating System :: OS Independent
Classifier: Topic :: Software Development :: Libraries :: Python Modules
